frc6343_scouting/__init__.py
frc6343_scouting/__main__.py
frc6343_scouting/cc_metrics.py
frc6343_scouting/season.py
frc6343_scouting/tbatool.py
tbatool/__init__.py
tbatool/cc_metrics.py
tbatool/tbatool.py
frc6343_scouting-0.7.dist-info/LICENSE
frc6343_scouting-0.7.dist-info/METADATA
frc6343_scouting-0.7.dist-info/WHEEL
frc6343_scouting-0.7.dist-info/entry_points.txt
frc6343_scouting-0.7.dist-info/top_level.txt
frc6343_scouting-0.7.dist-info/RECORD
