Metadata-Version: 2.1
Name: frc6343-scouting
Version: 0.7
Summary: A utility for analyzing Blue Alliance data
License: UNKNOWN
Platform: UNKNOWN
License-File: LICENSE
Requires-Dist: tbapy (==1.3.2)
Requires-Dist: pandas
Requires-Dist: numpy
Provides-Extra: test
Requires-Dist: pytest ; extra == 'test'
